{
    "remotePath": "/var/www/html/JW/kalambury",
    "host": "10.11.12.254",
    "username": "root",
    "port": 22,
    "secure": false,
    "protocol": "sftp",
    "uploadOnSave": true,
    "passive": false,
    "debug": false,
    "privateKeyPath": "C:\\Users\\sarap\\Desktop\\SSH\\RemoteFTP\\root@swiktor_nazwa_pl",
    "passphrase": null,
    "agent": null,
    "allow": [],
    "ignore": [
        "\\.vscode",
        "\\.git",
        "\\.DS_Store"
    ],
    "generatedFiles": {
        "extensionsToInclude": [
            ""
        ],
        "path": ""
    }
}